plotly_calplot/__init__.py
plotly_calplot/calplot.py
plotly_calplot/date_extractors.py
plotly_calplot/layout_formatter.py
plotly_calplot/raw_heatmap.py
plotly_calplot/single_year_calplot.py
plotly_calplot/utils.py
plotly_calplot-0.1.20.dist-info/METADATA
plotly_calplot-0.1.20.dist-info/WHEEL
plotly_calplot-0.1.20.dist-info/RECORD
