Metadata-Version: 2.1
Name: plotly_calplot
Version: 0.1.20
Summary: Calendar Plot made with Plotly
Home-page: https://github.com/brunorosilva/plotly-calplot
License: MIT
Author: Bruno Rodrigues Silva
Author-email: b.rosilva1@gmail.com
Requires-Python: >=3.8,<4.0.0
Classifier: License :: OSI Approved :: MIT License
Classifier: Programming Language :: Python :: 3
Classifier: Programming Language :: Python :: 3.8
Classifier: Programming Language :: Python :: 3.9
Classifier: Programming Language :: Python :: 3.10
Classifier: Programming Language :: Python :: 3.11
Classifier: Programming Language :: Python :: 3.12
Requires-Dist: numpy (>=1.22.3,<2.0.0)
Requires-Dist: pandas
Requires-Dist: plotly (>=5.4.0,<6.0.0)
Requires-Dist: pytz (>=2023.3.post1,<2024.0)
Project-URL: Repository, https://github.com/brunorosilva/plotly-calplot
